dagster_ray/__init__.py
dagster_ray/_version.py
dagster_ray/configs.py
dagster_ray/py.typed
dagster_ray/types.py
dagster_ray/utils.py
dagster_ray/_base/__init__.py
dagster_ray/_base/cluster_sharing_lock.py
dagster_ray/_base/constants.py
dagster_ray/_base/resources.py
dagster_ray/_base/utils.py
dagster_ray/core/__init__.py
dagster_ray/core/executor.py
dagster_ray/core/io_manager.py
dagster_ray/core/pipes.py
dagster_ray/core/resources.py
dagster_ray/core/run_launcher.py
dagster_ray/kuberay/__init__.py
dagster_ray/kuberay/configs.py
dagster_ray/kuberay/jobs.py
dagster_ray/kuberay/leader_election.py
dagster_ray/kuberay/ops.py
dagster_ray/kuberay/pipes.py
dagster_ray/kuberay/sensors.py
dagster_ray/kuberay/utils.py
dagster_ray/kuberay/client/__init__.py
dagster_ray/kuberay/client/base.py
dagster_ray/kuberay/client/raycluster/__init__.py
dagster_ray/kuberay/client/raycluster/client.py
dagster_ray/kuberay/client/rayjob/__init__.py
dagster_ray/kuberay/client/rayjob/client.py
dagster_ray/kuberay/resources/__init__.py
dagster_ray/kuberay/resources/base.py
dagster_ray/kuberay/resources/raycluster.py
dagster_ray/kuberay/resources/rayjob.py
dagster_ray-0.4.1.dist-info/METADATA
dagster_ray-0.4.1.dist-info/WHEEL
dagster_ray-0.4.1.dist-info/licenses/LICENSE
dagster_ray-0.4.1.dist-info/RECORD
