Metadata-Version: 2.4
Name: dagster-ray
Version: 0.4.1
Summary: Dagster integration library for Ray
Project-URL: GitHub, https://github.com/danielgafni/dagster-ray
Project-URL: Documentation, https://danielgafni.github.io/dagster-ray/
Project-URL: Changelog, https://github.com/danielgafni/dagster-ray/blob/main/CHANGELOG.md
Author-email: Daniel Gafni <danielgafni16@gmail.com>
License: Apache-2.0
License-File: LICENSE
Keywords: ETL,dagster,distributed,ray
Classifier: License :: OSI Approved :: Apache Software License
Classifier: Operating System :: OS Independent
Classifier: Programming Language :: Python :: 3.10
Classifier: Programming Language :: Python :: 3.11
Classifier: Programming Language :: Python :: 3.12
Classifier: Topic :: Software Development :: Libraries :: Python Modules
Requires-Python: <3.13,>=3.10
Requires-Dist: dagster>=1.10.0
Requires-Dist: eval-type-backport>=0.2.2; python_full_version < '3.10'
Requires-Dist: tenacity>=8.0.0
Provides-Extra: executor
Requires-Dist: ray[client]; extra == 'executor'
Provides-Extra: kuberay
Requires-Dist: dagster-k8s>=0.19.0; extra == 'kuberay'
Requires-Dist: kubernetes>=20.0.0; extra == 'kuberay'
Requires-Dist: pyyaml; extra == 'kuberay'
Requires-Dist: pyyaml>=4.0.0; extra == 'kuberay'
Provides-Extra: pipes
Requires-Dist: ray[client]; extra == 'pipes'
Provides-Extra: run-launcher
Requires-Dist: ray[client]; extra == 'run-launcher'
